rustmssql_python-0.1.6.dist-info/METADATA
rustmssql_python-0.1.6.dist-info/WHEEL
rustmssql_python/__init__.py
rustmssql_python/py.typed
rustmssql_python/rustmssql_python.cpython-39-aarch64-linux-gnu.so
rustmssql_python/rustmssql_python.pyi
rustmssql_python-0.1.6.dist-info/RECORD
