Metadata-Version: 2.4
Name: rustmssql_python
Version: 0.1.6
Classifier: Development Status :: 1 - Planning
Classifier: Natural Language :: Portuguese (Brazilian)
Classifier: Programming Language :: PL/SQL
Classifier: Programming Language :: Rust
Classifier: Programming Language :: Python :: Implementation :: CPython
Classifier: Programming Language :: Python :: Implementation :: PyPy
Requires-Dist: pytest ; extra == 'tests'
Provides-Extra: tests
Summary: Exporta consultas do SQL Server para arquivos Parquet de forma eficiente usando Rust.
Author-email: Marcus Holanda <mvsh777@hotmail.com>
Requires-Python: >=3.9
Project-URL: Codigo, https://github.com/Marcus-Holanda777/rustmssql-python
